simple_py_config/__init__.py
simple_py_config-0.0.1.dist-info/LICENSE
simple_py_config-0.0.1.dist-info/METADATA
simple_py_config-0.0.1.dist-info/WHEEL
simple_py_config-0.0.1.dist-info/top_level.txt
simple_py_config-0.0.1.dist-info/RECORD
